all_repos_depends/__init__.py
all_repos_depends/config.py
all_repos_depends/depends.py
all_repos_depends/errors.py
all_repos_depends/generate.py
all_repos_depends/packages.py
all_repos_depends/server.py
all_repos_depends/types.py
all_repos_depends/lang/__init__.py
all_repos_depends/lang/js.py
all_repos_depends/lang/python.py
all_repos_depends/templates/base.mako
all_repos_depends/templates/disambiguate.mako
all_repos_depends/templates/external.mako
all_repos_depends/templates/index.mako
all_repos_depends/templates/redirect.mako
all_repos_depends/templates/repo.mako
all_repos_depends-0.0.3.dist-info/LICENSE
all_repos_depends-0.0.3.dist-info/METADATA
all_repos_depends-0.0.3.dist-info/WHEEL
all_repos_depends-0.0.3.dist-info/entry_points.txt
all_repos_depends-0.0.3.dist-info/top_level.txt
all_repos_depends-0.0.3.dist-info/RECORD
