Metadata-Version: 2.1
Name: all-repos-depends
Version: 0.0.3
Summary: View the dependencies of your repositories.
Home-page: https://github.com/asottile/all-repos-depends
Author: Anthony Sottile
Author-email: asottile@umich.edu
License: MIT
Platform: UNKNOWN
Classifier: License :: OSI Approved :: MIT License
Classifier: Programming Language :: Python :: 3
Classifier: Programming Language :: Python :: 3 :: Only
Classifier: Programming Language :: Python :: 3.6
Classifier: Programming Language :: Python :: 3.7
Classifier: Programming Language :: Python :: 3.8
Requires-Python: >=3.6.1
Requires-Dist: all-repos (>=1.3.0)
Requires-Dist: flask
Requires-Dist: mako
Requires-Dist: packaging
